embedbase_client/__init__.py
embedbase_client/base.py
embedbase_client/client.py
embedbase_client/errors.py
embedbase_client/model.py
embedbase_client/split.py
embedbase_client/utils.py
embedbase_client-0.2.3.dist-info/LICENSE
embedbase_client-0.2.3.dist-info/METADATA
embedbase_client-0.2.3.dist-info/WHEEL
embedbase_client-0.2.3.dist-info/RECORD
