Metadata-Version: 2.1
Name: embedbase-client
Version: 0.2.3
Summary: Python client for Embedbase
Home-page: https://github.com/different-ai/embedbase/tree/main/sdk/embedbase-py
License: MIT
Keywords: embeddings,machine learning,artificial intelligence,llm
Author: Different AI
Author-email: louis@embedbase.xyz
Requires-Python: >=3.8,<4.0
Classifier: Development Status :: 4 - Beta
Classifier: Intended Audience :: Developers
Classifier: License :: OSI Approved :: MIT License
Classifier: Programming Language :: Python :: 3
Classifier: Programming Language :: Python :: 3.8
Classifier: Programming Language :: Python :: 3.9
Classifier: Programming Language :: Python :: 3.10
Classifier: Programming Language :: Python :: 3.11
Classifier: Topic :: Scientific/Engineering :: Artificial Intelligence
Requires-Dist: aiohttp (>=3.8.4,<4.0.0)
Requires-Dist: httpx (>=0.24.0,<0.25.0)
Requires-Dist: pydantic (>=1.10.7,<2.0.0)
Requires-Dist: tiktoken (>=0.3.3,<0.4.0)
Project-URL: Repository, https://github.com/different-ai/embedbase/tree/main/sdk/embedbase-py
